{
  "id": "omni_mark_fight",
  "title": "全能人vs无敌少侠·诺兰离开地球",
  "source": "动画S1E8",
  "trigger": "护卫队覆灭后2-3天。诺兰痊愈速度暴露伪装。永生侠复活指控。马克当面质问父亲。",
  "expires_days": 365,
  "repeatable": false,
  "hook": {
    "text": "诺兰在GDA总部对马克揭露维特鲁姆帝国真相。马克拒绝加入。战斗从GDA打到芝加哥。 地铁列车名场面：诺兰按住马克的脸拖过整列满员地铁，数百人死亡。 诺兰：「再过17年又怎样？我可以重新开始。再生一个。」 马克满嘴是血：「就算那样…我也还有你，爸。」诺兰愣住。松手。飞离地球。 【公众所见】芝加哥大屠杀被全球直播，但直播只拍到战斗画面。公众看到全能人疯狂杀戮，一个新英雄「无敌少侠」拼死抵抗。公众不知道全能人=诺兰·格雷森（作家），不知道无敌少侠=马克·格雷森（诺兰的儿子）。 Cecil事后掩盖：对外宣布作家诺兰·格雷森死于车祸。同时配合媒体将芝加哥事件定性为「全能人精神崩溃后失控」，隐瞒维特鲁姆帝国渗透的真相。 数万人死亡。芝加哥大面积被毁。黛比和马克以「死去的作家的家属」身份继续生活，但媒体开始猜测无敌少侠和全能人的能力过于相似。",
    "urgency": 5
  },
  "iconic_scenes": "地铁列车名场面：诺兰按住马克的脸拖过整列满员地铁。 名台词诺兰：「再过17年又怎样？我可以重新开始。再生一个。」 名台词马克：「就算那样…我也还有你，爸。」诺兰松手，飞走。",
  "perception_levels": [
    {
      "level": 1,
      "text": "全球新闻直播了芝加哥的战斗和破坏。直升机拍到全能人摧毁建筑、和无敌少侠交战，但录不到他们的对话。 媒体最初称无敌少侠为「不明英雄」，后确认代号。全能人的屠杀引发全球恐慌和愤怒。 第二天所有报纸头条：全人类最强大的守护者变成了最可怕的噩梦。 政府声明：全能人已死亡（实际上飞离地球）。作家诺兰·格雷森（全能人的秘密身份，公众不知）被宣布死于车祸。"
    },
    {
      "level": 2,
      "text": "你在芝加哥或附近。大楼晃动。天上全能人在和一个蒙面的新英雄打斗。 地铁全停。疏散人群。混凝土粉尘和焦电线味。 你不知道那个新英雄是谁。你不知道全能人还有个儿子。你只知道你在逃命。 战力≥城市级→应该介入吗？战力不足→逃命。"
    },
    {
      "level": 3,
      "text": "你在现场或GDA成员/英雄/认识马克或黛比。 Cecil呼叫：「我需要所有能飞能打的人去芝加哥。现在。」 战斗后你看到无敌少侠，浑身是血。你听说诺兰·格雷森（作家）今天「死于车祸」。你注意到他儿子的照片和无敌少侠的体型很像。你不能确定。"
    },
    {
      "level": 4,
      "text": "你介入战斗。干扰诺兰→不一定赢但改变马克受伤程度。 救了地铁里的人→马克没有被血肉碎片击垮的那一幕。 诺兰评估你的战力。帝国会在后续计划中列入你的名字。"
    }
  ],
  "on_expire": "公众对超英看法:-30(累计-50)。Heat:公开参与→+30。Collateral:若在芝加哥→增加。 维特鲁姆帝国好感度:仍0(诺兰单独行动)。 【公众未知】全能人=诺兰·格雷森。无敌少侠=诺兰的儿子。",
  "hooks_text": "黛比被告知丈夫死于车祸。她在咖啡杯旁坐了一天。马克以无敌少侠身份受Cecil联络，公众不知道他是诺兰的儿子。 Cecil收拾残局。媒体怀疑无敌少侠和全能人的能力来源相同。你需要介入吗？ 如果你知道真相（无敌少侠=诺兰的儿子），你告诉谁？"
}